<?xml version="1.0" encoding="UTF-8"?>
<!DOCTYPE mapper PUBLIC "-//mybatis.org//DTD Mapper 3.0//EN" "http://mybatis.org/dtd/mybatis-3-mapper.dtd">
<mapper namespace="com.imm.dao.OfflineMessageMapper">
  <resultMap id="BaseResultMap" type="com.imm.model.po.OfflineMessage">
    <!--
      WARNING - @mbg.generated
      This element is automatically generated by MyBatis Generator, do not modify.
    -->
    <constructor>
      <idArg column="id" javaType="java.lang.Integer" jdbcType="INTEGER" />
      <arg column="messagefrom" javaType="java.lang.Integer" jdbcType="INTEGER" />
      <arg column="messageto" javaType="java.lang.Integer" jdbcType="INTEGER" />
      <arg column="messagecontent" javaType="java.lang.String" jdbcType="VARCHAR" />
      <arg column="messagestatus" javaType="java.lang.String" jdbcType="CHAR" />
      <arg column="addtime" javaType="java.util.Date" jdbcType="TIMESTAMP" />
      <arg column="updatetime" javaType="java.util.Date" jdbcType="TIMESTAMP" />
    </constructor>
  </resultMap>
  <sql id="Base_Column_List">
    <!--
      WARNING - @mbg.generated
      This element is automatically generated by MyBatis Generator, do not modify.
    -->
    id, messagefrom, messageto, messagecontent, messagestatus, addtime, updatetime
  </sql>
  <insert id="insertSelective" parameterType="com.imm.model.po.OfflineMessage">
    <!--
      WARNING - @mbg.generated
      This element is automatically generated by MyBatis Generator, do not modify.
    -->
    insert into offline_message
    <trim prefix="(" suffix=")" suffixOverrides=",">
      <if test="id != null">
        id,
      </if>
      <if test="messagefrom != null">
        messagefrom,
      </if>
      <if test="messageto != null">
        messageto,
      </if>
      <if test="messagecontent != null">
        messagecontent,
      </if>
      <if test="messagestatus != null">
        messagestatus,
      </if>
      <if test="addtime != null">
        addtime,
      </if>
      <if test="updatetime != null">
        updatetime,
      </if>
    </trim>
    <trim prefix="values (" suffix=")" suffixOverrides=",">
      <if test="id != null">
        #{id,jdbcType=INTEGER},
      </if>
      <if test="messagefrom != null">
        #{messagefrom,jdbcType=INTEGER},
      </if>
      <if test="messageto != null">
        #{messageto,jdbcType=INTEGER},
      </if>
      <if test="messagecontent != null">
        #{messagecontent,jdbcType=VARCHAR},
      </if>
      <if test="messagestatus != null">
        #{messagestatus,jdbcType=CHAR},
      </if>
      <if test="addtime != null">
        #{addtime,jdbcType=TIMESTAMP},
      </if>
      <if test="updatetime != null">
        #{updatetime,jdbcType=TIMESTAMP},
      </if>
    </trim>
  </insert>
  <update id="updateByPrimaryKeySelective" parameterType="com.imm.model.po.OfflineMessage">
    <!--
      WARNING - @mbg.generated
      This element is automatically generated by MyBatis Generator, do not modify.
    -->
    update offline_message
    <set>
      <if test="messagefrom != null">
        messagefrom = #{messagefrom,jdbcType=INTEGER},
      </if>
      <if test="messageto != null">
        messageto = #{messageto,jdbcType=INTEGER},
      </if>
      <if test="messagecontent != null">
        messagecontent = #{messagecontent,jdbcType=VARCHAR},
      </if>
      <if test="messagestatus != null">
        messagestatus = #{messagestatus,jdbcType=CHAR},
      </if>
      <if test="addtime != null">
        addtime = #{addtime,jdbcType=TIMESTAMP},
      </if>
      <if test="updatetime != null">s
        updatetime = #{updatetime,jdbcType=TIMESTAMP},
      </if>
    </set>
    where id = #{id,jdbcType=INTEGER}
  </update>
    <select id="getOfflineMessageByAccout" resultType="com.imm.model.po.OfflineMessage">
        SELECT
        <include refid="Base_Column_List" />
        FROM offline_message om WHERE 0=0 AND om.messagestatus = #{status,jdbcType=VARCHAR} AND om.messageto = #{account,jdbcType=VARCHAR}
    </select>
</mapper>